libresprite_mcp/__init__.py
libresprite_mcp/libresprite_proxy.py
libresprite_mcp/mcp_server.py
libresprite_mcp/resources/examples.txt
libresprite_mcp/resources/reference.txt
libresprite_mcp-0.1.3.dist-info/WHEEL
libresprite_mcp-0.1.3.dist-info/entry_points.txt
libresprite_mcp-0.1.3.dist-info/METADATA
libresprite_mcp-0.1.3.dist-info/RECORD
