Metadata-Version: 2.3
Name: libresprite-mcp
Version: 0.1.3
Summary: Prompt your way into LibreSprite
Author: Snehil Shah
Author-email: Snehil Shah <snehilshah.989@gmail.com>
Requires-Dist: flask>=3.1.1
Requires-Dist: mcp[cli]>=1.12.2
Requires-Python: >=3.11
